parquet_to_excel-0.7.2.dist-info/METADATA
parquet_to_excel-0.7.2.dist-info/WHEEL
parquet_to_excel-0.7.2.dist-info/licenses/LICENSE
parquet_to_excel/__init__.py
parquet_to_excel/parquet_to_excel.cp312-win_amd64.pyd
parquet_to_excel-0.7.2.dist-info/RECORD
