Metadata-Version: 2.4
Name: parquet_to_excel
Version: 0.7.2
Classifier: Programming Language :: Rust
Classifier: Programming Language :: Python :: Implementation :: CPython
Classifier: Programming Language :: Python :: Implementation :: PyPy
License-File: LICENSE
Summary: a crate to convert parquet file(s) to an/a excel/csv file with constant memory in rust
Keywords: csv,xlsx,excel,parquet,convert
License: MIT
Requires-Python: >=3.8
Project-URL: Source Code, https://gitee.com/sone92/paruqet-to-xlsx.git
